tronclient/__init__.py
tronclient/main.py
tronclient-0.0.1.dist-info/LICENSE.txt
tronclient-0.0.1.dist-info/METADATA
tronclient-0.0.1.dist-info/WHEEL
tronclient-0.0.1.dist-info/top_level.txt
tronclient-0.0.1.dist-info/RECORD
