Metadata-Version: 2.1
Name: tronclient
Version: 0.0.1
Summary: tronclinet library for Python
Author: victortron
Author-email: vesite1094@agiuse.com
License: MIT
Project-URL: Source Repository, https://github.com
License-File: LICENSE.txt
Requires-Dist: requests
